ram_example.v
module ram_example(
    addr,
    wr,
    clk,
    data_in,
    data_out,
    set_mem);

    input       clk, wr, set_mem;
    input[0:3]  data_in;
    input[0:2]  addr;
    input[0:3]  data_out;
    reg  [0:3]  data_out_temp;
    reg  [0:3]  mem [0:3];

    always @(negedge clk)
    begin
        if (set_mem == 1'b0)
        begin
            mem[0] = 4'b0010;
            mem[1] = 4'b0011;
            mem[2] = 4'b0100;
            mem[3] = 4'b0101;
        end

        if (wr == 1'b1)
        begin
            mem[addr] <= data_in;
        end
        else if (wr == 1'b0)
        begin
            data_out_temp = mem[addr];
        end
    end
    assign data_out = data_out_temp;
endmodule

ram_tb.v
module ram_tb;
    reg         clk, wr, set_mem;
    reg  [0:3]  data_in;
    reg  [0:2]  addr;
    wire [0:3]  data_out;

    initial begin
        $dumpfile("ram_tb.vcd");
        $dumpvars(0, ram_tb);
    end

    ram_example ram_1(
        .addr(addr),
        .wr(wr),
        .clk(clk),
        .data_in(data_in),
        .data_out(data_out),
        .set_mem(set_mem)
    );

    always #5 clk = ~clk;

    initial begin
        clk <= 1'b1;
        set_mem = 1'b0;
        for (addr = 0; addr <= 3; addr = addr + 1)
        begin
            wr = 1'b0;
            repeat(2) @ (negedge clk);
        end
        set_mem = 1'b1;
        for (addr = 0; addr <= 3; addr = addr + 1)
        begin
            wr = 1'b1;
            data_in = addr;
            repeat(2) @ (negedge clk);
            wr = 1'b0;
            repeat(2) @ (negedge clk);
        end
        
        $finish;
    end
endmodule

ram_tb.vcd
$date
	Fri May 14 20:51:40 2021
$end
$version
	Icarus Verilog
$end
$timescale
	1s
$end
$scope module ram_tb $end
$var wire 4 ! data_out [0:3] $end
$var reg 3 " addr [0:2] $end
$var reg 1 # clk $end
$var reg 4 $ data_in [0:3] $end
$var reg 1 % set_mem $end
$var reg 1 & wr $end
$scope module ram_1 $end
$var wire 3 ' addr [0:2] $end
$var wire 1 # clk $end
$var wire 4 ( data_in [0:3] $end
$var wire 4 ) data_out [0:3] $end
$var wire 1 % set_mem $end
$var wire 1 & wr $end
$var reg 4 * data_out_temp [0:3] $end
$upscope $end
$upscope $end
$enddefinitions $end
#0
$dumpvars
bx *
bx )
bx (
b0 '
0&
0%
bx $
1#
b0 "
bx !
$end
#5
b10 !
b10 )
b10 *
0#
#10
1#
#15
b1 "
b1 '
0#
#20
1#
#25
b11 !
b11 )
b11 *
0#
#30
1#
#35
b10 "
b10 '
0#
#40
1#
#45
b100 !
b100 )
b100 *
0#
#50
1#
#55
b11 "
b11 '
0#
#60
1#
#65
b101 !
b101 )
b101 *
0#
#70
1#
#75
b0 $
b0 (
1&
1%
b0 "
b0 '
0#
#80
1#
#85
0#
#90
1#
#95
0&
0#
#100
1#
#105
b0 !
b0 )
b0 *
0#
#110
1#
#115
b1 $
b1 (
1&
b1 "
b1 '
0#
#120
1#
#125
0#
#130
1#
#135
0&
0#
#140
1#
#145
b1 !
b1 )
b1 *
0#
#150
1#
#155
b10 $
b10 (
1&
b10 "
b10 '
0#
#160
1#
#165
0#
#170
1#
#175
0&
0#
#180
1#
#185
b10 !
b10 )
b10 *
0#
#190
1#
#195
b11 $
b11 (
1&
b11 "
b11 '
0#
#200
1#
#205
0#
#210
1#
#215
0&
0#
#220
1#
#225
b11 !
b11 )
b11 *
0#
#230
1#
#235
b100 "
b100 '
0#
